zwjira/__init__.py
zwjira/cli.py
zwjira/commands.py
zwjira/config.py
zwjira/globals.py
zwjira/jira.py
zwjira/xray.py
zwjira-0.1.1.dist-info/entry_points.txt
zwjira-0.1.1.dist-info/LICENSE
zwjira-0.1.1.dist-info/WHEEL
zwjira-0.1.1.dist-info/METADATA
zwjira-0.1.1.dist-info/RECORD
